seaBlock/__init__.py
seaBlock-0.5.dist-info/METADATA
seaBlock-0.5.dist-info/WHEEL
seaBlock-0.5.dist-info/top_level.txt
seaBlock-0.5.dist-info/RECORD
