Metadata-Version: 2.1
Name: seaBlock
Version: 0.5
Summary: Sanctioned Encryption Algorithm (SEA)
Author: Ritul(void)
Author-email: codebyritul@gmail.com
Classifier: Programming Language :: Python :: 3
Classifier: License :: OSI Approved :: MIT License
Classifier: Operating System :: OS Independent
Requires-Python: >=3.6
Requires-Dist: pycryptodome
